SearchEngineForJSON/__init__.py
SearchEngineForJSON/search.py
testSearchEngineForJSON/__init__.py
testSearchEngineForJSON/test_search.py
SearchEngineForJSON-0.1.14.dist-info/LICENSE
SearchEngineForJSON-0.1.14.dist-info/METADATA
SearchEngineForJSON-0.1.14.dist-info/WHEEL
SearchEngineForJSON-0.1.14.dist-info/top_level.txt
SearchEngineForJSON-0.1.14.dist-info/RECORD
