Metadata-Version: 2.1
Name: SearchEngineForJSON
Version: 0.1.14
Summary: SearchEngineForJSON
Home-page: https://github.com/aoimaru/packagingTutorial
Author: AoiNakamura
Author-email: example@gmail.com
License: UNKNOWN
Platform: UNKNOWN
Classifier: Programming Language :: Python :: 3
Requires-Python: >=3.7
